nevax/__init__.py
nevax/attend.py
nevax/model.py
nevax/transformer.py
nevax-0.1.4.dist-info/LICENSE
nevax-0.1.4.dist-info/WHEEL
nevax-0.1.4.dist-info/METADATA
nevax-0.1.4.dist-info/RECORD
