Metadata-Version: 2.1
Name: nevax
Version: 0.1.4
Summary: NeVA: NVIDIA's Visual Question Answering Transformer
Home-page: https://github.com/kyegomez/neva
License: Attribution-NonCommercial 4.0 International
Author: Kye Gomez
Author-email: kye@apac.ai
Requires-Python: >=3.6,<4.0
Classifier: License :: Other/Proprietary License
Classifier: Programming Language :: Python :: 3
Classifier: Programming Language :: Python :: 3.6
Classifier: Programming Language :: Python :: 3.7
Classifier: Programming Language :: Python :: 3.8
Classifier: Programming Language :: Python :: 3.9
Classifier: Programming Language :: Python :: 3.10
Classifier: Programming Language :: Python :: 3.11
Requires-Dist: einops
Requires-Dist: torch
Requires-Dist: transformers
Project-URL: Repository, https://github.com/kyegomez/neva
